pgsignals/__init__.py
pgsignals/apps.py
pgsignals/enums.py
pgsignals/event.py
pgsignals/signals.py
pgsignals/sql.py
pgsignals/utils.py
pgsignals/management/__init__.py
pgsignals/management/commands/runpgsignals.py
pgsignals-0.3.7.dist-info/LICENSE.txt
pgsignals-0.3.7.dist-info/METADATA
pgsignals-0.3.7.dist-info/WHEEL
pgsignals-0.3.7.dist-info/top_level.txt
pgsignals-0.3.7.dist-info/RECORD
