Metadata-Version: 2.1
Name: pgsignals
Version: 0.3.7
Summary: Allows handle PostgreSQL notifies via listener as regular Django signal.
Home-page: https://github.com/gtors/django-pgsignals/
Author: gtors
Author-email: andrey.torsunov@gmail.com
License: mit
Platform: any
Classifier: Development Status :: 4 - Beta
Classifier: Intended Audience :: Developers
Classifier: License :: OSI Approved :: MIT License
Classifier: Programming Language :: Python :: 3.7
Requires-Python: >=3.7
Requires-Dist: psycopg2-binary
Requires-Dist: django-appconf
